{
   "dependencies": [
      {
         "name": "lime",
         "type": "install",
         "version": null
      },
      {
         "name": "flixel",
         "type": "install",
         "version": "5.0.0"
      },
      {
         "name": "flixel-addons",
         "type": "install",
         "version": "3.1.1"
      },
      {
         "name": "flixel-ui",
         "type": "install",
         "version": "2.5.0"
      },
      {
         "name": "openfl",
         "type": "install",
         "version": null
      },
      {
         "name": "hxcpp",
         "type": "install",
         "version": null
      },
      {
         "name": "hscript",
         "type": "install",
         "version": null
      },
      {
         "name": "haxeui-core",
         "type": "install",
         "version": null
      },
      {
         "name": "haxeui-flixel",
         "type": "install",
         "version": null
      },
      {
         "name": "hxcpp-debug-server",
         "type": "install",
         "version": null
      },
      {
         "name": "discord_rpc",
         "type": "git",
         "dir": null,
         "ref": "master",
         "url": "https://github.com/Aidan63/linc_discord-rpc"
      }
   ]
}